betterlib/__init__.py
betterlib/config.py
betterlib/ip.py
betterlib/logging.py
betterlib/quik.py
betterlib/threader.py
betterlib-0.2.0.dist-info/LICENSE
betterlib-0.2.0.dist-info/METADATA
betterlib-0.2.0.dist-info/WHEEL
betterlib-0.2.0.dist-info/top_level.txt
betterlib-0.2.0.dist-info/RECORD
