Metadata-Version: 2.1
Name: betterlib
Version: 0.2.0
Summary: A useful collection of various tools and libraries for anyone to use in their projects.
Author-email: Henry Martin <n3rdl0rd@proton.me>
Project-URL: Homepage, https://github.com/HENRYMARTIN5/betterlib
Project-URL: Bug Tracker, https://github.com/HENRYMARTIN5/betterlib/issues
Classifier: Programming Language :: Python :: 3
Classifier: License :: OSI Approved :: The Unlicense (Unlicense)
Classifier: Operating System :: OS Independent
Requires-Python: >=3.5
License-File: LICENSE
Requires-Dist: requests (==2.28.1)
Requires-Dist: colorama (==0.4.6)
